Metadata-Version: 1.1
Name: slugid
Version: 1.0.2
Summary: Base64 encoded uuid v4 slugs
Home-page: http://taskcluster.github.io/slugid.py
Author: Pete Moore
Author-email: pmoore@mozilla.com
License: MPL 2.0
Platform: UNKNOWN
Classifier: Intended Audience :: Developers
Classifier: Natural Language :: English
